[{"place_id": 236326225, "licence": "Data \u00a9 OpenStreetMap contributors, ODbL 1.0. http://osm.org/copyright", "osm_type": "way", "osm_id": 173221554, "lat": "1.3530295", "lon": "103.9453532", "class": "building", "type": "train_station", "place_rank": 30, "importance": 8.432822156095243e-05, "addresstype": "building", "name": "Tampines MRT Station", "display_name": "Tampines MRT Station, 20, Tampines Central 1, Tampines East, Tampines, East Region, Singapore, 529538, Singapore", "boundingbox": ["1.3526267", "1.3538352", "103.9446600", "103.9457151"]}]