[{"place_id": 236105263, "licence": "Data \u00a9 OpenStreetMap contributors, ODbL 1.0. http://osm.org/copyright", "osm_type": "node", "osm_id": 4302905987, "lat": "1.2836965", "lon": "103.8607226", "class": "tourism", "type": "hotel", "place_rank": 30, "importance": 0.46658588691550174, "addresstype": "tourism", "name": "Marina Bay Sands", "display_name": "Marina Bay Sands, 10, Bayfront Avenue, Bayfront Subzone, Downtown Core, Central Region, Singapore, 018956, Singapore", "boundingbox": ["1.2836465", "1.2837465", "103.8606726", "103.8607726"]}]